README.md
setup.cfg
setup.py
sre_bot.egg-info/PKG-INFO
sre_bot.egg-info/SOURCES.txt
sre_bot.egg-info/dependency_links.txt
sre_bot.egg-info/entry_points.txt
sre_bot.egg-info/requires.txt
sre_bot.egg-info/top_level.txt
srebot/__init__.py
srebot/bot.py
srebot/config.py
srebot/install_services.py
srebot/mqtt_tools.py
srebot/tools.py
srebot/webserver.py
srebot/datafiles/bot.template.py
srebot/datafiles/sre.service