Metadata-Version: 2.1
Name: sre-bot
Version: 0.1.12
Summary: Data collector / executor - Site Reliability Framework
Home-page: https://github.com/marcwimmer/sre-bot
Author: Marc-Christian Wimmer
License: MIT
Platform: UNKNOWN
Requires-Python: >=3.6.0
